{
  "number": 38,
  "text": {
    "ar": "وَٱتَّبَعۡتُ مِلَّةَ ءَابَآءِيٓ إِبۡرَٰهِيمَ وَإِسۡحَٰقَ وَيَعۡقُوبَۚ مَا كَانَ لَنَآ أَن نُّشۡرِكَ بِٱللَّهِ مِن شَيۡءٖۚ ذَٰلِكَ مِن فَضۡلِ ٱللَّهِ عَلَيۡنَا وَعَلَى ٱلنَّاسِ وَلَٰكِنَّ أَكۡثَرَ ٱلنَّاسِ لَا يَشۡكُرُونَ",
    "en": "And I have followed the religion of my fathers, Abraham, Isaac and Jacob. And it was not for us to associate anything with Allah. That is from the favor of Allah upon us and upon the people, but most of the people are not grateful"
  },
  "juz": 12,
  "page": 240,
  "sajda": false
}
