{
  "number": 5,
  "text": {
    "ar": "وَٱخۡتِلَٰفِ ٱلَّيۡلِ وَٱلنَّهَارِ وَمَآ أَنزَلَ ٱللَّهُ مِنَ ٱلسَّمَآءِ مِن رِّزۡقٖ فَأَحۡيَا بِهِ ٱلۡأَرۡضَ بَعۡدَ مَوۡتِهَا وَتَصۡرِيفِ ٱلرِّيَٰحِ ءَايَٰتٞ لِّقَوۡمٖ يَعۡقِلُونَ",
    "en": "And [in] the alternation of night and day and [in] what Allah sends down from the sky of provision and gives life thereby to the earth after its lifelessness and [in His] directing of the winds are signs for a people who reason"
  },
  "juz": 25,
  "page": 499,
  "sajda": false
}
