{
  "number": 4,
  "text": {
    "ar": "قُلۡ أَرَءَيۡتُم مَّا تَدۡعُونَ مِن دُونِ ٱللَّهِ أَرُونِي مَاذَا خَلَقُواْ مِنَ ٱلۡأَرۡضِ أَمۡ لَهُمۡ شِرۡكٞ فِي ٱلسَّمَٰوَٰتِۖ ٱئۡتُونِي بِكِتَٰبٖ مِّن قَبۡلِ هَٰذَآ أَوۡ أَثَٰرَةٖ مِّنۡ عِلۡمٍ إِن كُنتُمۡ صَٰدِقِينَ",
    "en": "Say, [O Muhammad], \"Have you considered that which you invoke besides Allah? Show me what they have created of the earth; or did they have partnership in [creation of] the heavens? Bring me a scripture [revealed] before this or a [remaining] trace of knowledge, if you should be truthful"
  },
  "juz": 26,
  "page": 502,
  "sajda": false
}
